queryshield_probe/__init__.py
queryshield_probe/api_client.py
queryshield_probe/budgets.py
queryshield_probe/capture.py
queryshield_probe/classify.py
queryshield_probe/cost_analysis.py
queryshield_probe/explain_checks.py
queryshield_probe/explain_mysql.py
queryshield_probe/explain_pg.py
queryshield_probe/report.py
queryshield_probe/utils.py
queryshield_probe/runners/django_runner.py
queryshield_probe/runners/pytest_plugin.py
queryshield_probe-0.3.0.dist-info/METADATA
queryshield_probe-0.3.0.dist-info/WHEEL
queryshield_probe-0.3.0.dist-info/RECORD
