Metadata-Version: 2.4
Name: queryshield-probe
Version: 0.3.0
Summary: Django DB query probe for QueryShield
Project-URL: Homepage, https://example.com/queryshield
Author-email: QueryShield <dev@queryshield.io>
Requires-Python: >=3.9
Requires-Dist: django>=4.2
Requires-Dist: pyyaml>=6.0
